picguard-1.0.0rc0.dist-info/METADATA
picguard-1.0.0rc0.dist-info/WHEEL
picguard/__init__.py
picguard-1.0.0rc0.dist-info/RECORD
