Metadata-Version: 2.1
Name: picguard
Version: 1.0.0rc0
Summary: Your pictures, your signature.
Author-Email: kjxbyz <kjxbyz888@outlook.com>
License: MIT
Requires-Python: >=3.9
